zerocrypt/__init__.py
zerocrypt/cmdline.py
zerocrypt/libcrypto.so
zerocrypt-0.2.dist-info/LICENSE
zerocrypt-0.2.dist-info/METADATA
zerocrypt-0.2.dist-info/WHEEL
zerocrypt-0.2.dist-info/top_level.txt
zerocrypt-0.2.dist-info/RECORD
